ttkthemes2/__init__.py
ttkthemes2/awthemes-10.4.0/awarc.tcl
ttkthemes2/awthemes-10.4.0/awblack.tcl
ttkthemes2/awthemes-10.4.0/awbreeze.tcl
ttkthemes2/awthemes-10.4.0/awbreezedark.tcl
ttkthemes2/awthemes-10.4.0/awclearlooks.tcl
ttkthemes2/awthemes-10.4.0/awdark.tcl
ttkthemes2/awthemes-10.4.0/awlight.tcl
ttkthemes2/awthemes-10.4.0/awtemplate.tcl
ttkthemes2/awthemes-10.4.0/awthemes.n7
ttkthemes2/awthemes-10.4.0/awthemes.tcl
ttkthemes2/awthemes-10.4.0/awwinxpblue.tcl
ttkthemes2/awthemes-10.4.0/colorutils.tcl
ttkthemes2/awthemes-10.4.0/demoscaled.tcl
ttkthemes2/awthemes-10.4.0/demoscaledb.tcl
ttkthemes2/awthemes-10.4.0/demottk.tcl
ttkthemes2/awthemes-10.4.0/i/awthemes/arrow/chevron/arrow-down-d.svg
ttkthemes2/awthemes-10.4.0/i/awthemes/arrow/chevron/arrow-down-n-base.svg
ttkthemes2/awthemes-10.4.0/i/awthemes/arrow/chevron/arrow-down-n.svg
ttkthemes2/awthemes-10.4.0/i/awthemes/arrow/chevron/arrow-down-sn.svg
ttkthemes2/awthemes-10.4.0/i/awthemes/arrow/chevron/arrow-left-n.svg
ttkthemes2/awthemes-10.4.0/i/awthemes/arrow/chevron/arrow-right-n.svg
ttkthemes2/awthemes-10.4.0/i/awthemes/arrow/chevron/arrow-right-sn.svg
ttkthemes2/awthemes-10.4.0/i/awthemes/arrow/chevron/arrow-up-d.svg
ttkthemes2/awthemes-10.4.0/i/awthemes/arrow/chevron/arrow-up-n.svg
ttkthemes2/awthemes-10.4.0/i/awthemes/arrow/open/arrow-down-n-base.svg
ttkthemes2/awthemes-10.4.0/i/awthemes/arrow/open/arrow-down-n.svg
ttkthemes2/awthemes-10.4.0/i/awthemes/arrow/open/arrow-down-sn.svg
ttkthemes2/awthemes-10.4.0/i/awthemes/arrow/open/arrow-left-n.svg
ttkthemes2/awthemes-10.4.0/i/awthemes/arrow/open/arrow-right-n.svg
ttkthemes2/awthemes-10.4.0/i/awthemes/arrow/open/arrow-right-sn.svg
ttkthemes2/awthemes-10.4.0/i/awthemes/arrow/open/arrow-up-n.svg
ttkthemes2/awthemes-10.4.0/i/awthemes/arrow/solid/arrow-down-n-base.svg
ttkthemes2/awthemes-10.4.0/i/awthemes/arrow/solid/arrow-down-n.svg
ttkthemes2/awthemes-10.4.0/i/awthemes/arrow/solid/arrow-down-sn.svg
ttkthemes2-0.1.0.dist-info/METADATA
ttkthemes2-0.1.0.dist-info/WHEEL
ttkthemes2-0.1.0.dist-info/RECORD
